uhina/__init__.py
uhina/_modidx.py
uhina/cli.py
uhina/loading.py
uhina/preprocessing.py
uhina/wavelets.py
uhina-0.0.3.dist-info/LICENSE
uhina-0.0.3.dist-info/METADATA
uhina-0.0.3.dist-info/WHEEL
uhina-0.0.3.dist-info/entry_points.txt
uhina-0.0.3.dist-info/top_level.txt
uhina-0.0.3.dist-info/RECORD
